authtools/__init__.py
authtools/admin.py
authtools/backends.py
authtools/forms.py
authtools/models.py
authtools/urls.py
authtools/views.py
authtools/migrations/0001_initial.py
authtools/migrations/0002_django18.py
authtools/migrations/0003_auto_20160128_0912.py
authtools/migrations/__init__.py
olivia_django_authtools-1.0.0.dist-info/DESCRIPTION.rst
olivia_django_authtools-1.0.0.dist-info/METADATA
olivia_django_authtools-1.0.0.dist-info/RECORD
olivia_django_authtools-1.0.0.dist-info/WHEEL
olivia_django_authtools-1.0.0.dist-info/metadata.json
olivia_django_authtools-1.0.0.dist-info/top_level.txt
